fastBloomFilter/__init__.py
fastBloomFilter/bloom.py
fastBloomFilter/loadbloom.py
fastBloomFilter/mkbloom.py
fastBloomFilter-0.0.11.dist-info/LICENSE
fastBloomFilter-0.0.11.dist-info/METADATA
fastBloomFilter-0.0.11.dist-info/WHEEL
fastBloomFilter-0.0.11.dist-info/top_level.txt
fastBloomFilter-0.0.11.dist-info/RECORD
