Metadata-Version: 2.1
Name: fastBloomFilter
Version: 0.0.11
Summary: A fast and simple probabilistic bloom filter that supports compression
Home-page: http://github.com/daedalus/bloomfilter
Author: Dario Clavijo
Author-email: dclavijo@protonmail.com
License: UNKNOWN
Download-URL: http://github.com/daedalus/bloomfilter/tarball/0.0.11
Platform: UNKNOWN
Classifier: Development Status :: 1 - Planning
Classifier: Intended Audience :: Developers
Classifier: Programming Language :: Python
Classifier: Operating System :: OS Independent
Classifier: License :: OSI Approved :: GNU General Public License (GPL)
Requires-Dist: bitarray
Requires-Dist: python-lzo
Requires-Dist: lz4
Requires-Dist: pylzma
Requires-Dist: sha3
